{"agent":"adversarial_c_tone_mismatch","score":6,"verdict":"marginal","issues":["cool_color_temperature_conflicts_with_warm_sunny_target","reads_generic_rpg_gem_rather_than_whimsical_hyrule","peer_references_are_dark_militaristic_helmets_misaligned_with_fairy_tale_target","lacks_distinctive_nintendo_charm_sparkle"],"reasoning":"Candidate (right, 4x): a pixel-art sapphire gem in vivid cool blue with white highlight facets. It is not grimdark, not edgy, not corporate — it reads as a clean, competent pixel RPG collectible. However, the color temperature is notably cold/icy rather than the warm-sunny palette the target aesthetic demands. The highlight style is generic RPG inventory art rather than toy-diorama whimsy. Peer references (left) are a grid of dark metallic helmets — mostly gray dungeon-crawler armor — which themselves skew away from the bright/friendly Hyrule target, making side-by-side tonal comparison difficult; the helmets arguably pull the composition colder. The gem alone would not fail a Nintendo tone test outright, but it does not radiate the 'warm fairy-tale sparkle' of Echoes or Link's Awakening gem icons. No occult, fan-service, or GRIMDARK flags. The marginal score reflects a neutral-to-cool drift rather than an active tone violation.","confidence":0.72}