{"agent":"aesthetic_c_color_harmony","score":5,"verdict":"marginal","issues":["cold_neutral_grey_background_violates_colored_darks_rule","overall_low_saturation_no_vivid_accent_colors","missing_bright_palette_members_greens_blues_oranges_pinks"],"reasoning":"The button frame uses warm parchment gold and warm brown tones that are compatible with the Echoes palette, and the face shadow uses warm dark brown rather than pure black — these are correct. However, the thumbnail/staging background is a cold neutral grey (approx #404045), which directly violates the 'shadows are colored darks, NEVER pure black/grey' rule. The overall image mood reads earthy/muted rather than BRIGHT/WARM: the dominant parchment beige is low-saturation, and none of the palette's signature saturated members (sky blue, candy pink, sunset orange, vivid green) appear anywhere. The piece feels like a placeholder tone study rather than a fully-committed Echoes-palette asset. Warming the background to deep teal or warm plum and introducing at least one saturated accent on the button would push this to a pass.","confidence":0.82}