{"agent":"adversarial_a_artifact_hunter","score":6,"verdict":"marginal","issues":["aa_edges_circular_boundary","scattered_perimeter_noise_pixels","outer_ring_gradient_exceeds_hard_tone_limit"],"reasoning":"Pixel art style is mostly clean with proper stairstepped circular edges and flat color regions. However, three tells detected: (1) AA-style edge blending at the circular boundary between the beige outer ring and the dark background — several intermediate-tone pixels that read as anti-aliasing rather than intentional pixel art dithering; (2) scattered isolated pixels (blue/light) around the lower-right perimeter that don't align with the otherwise-regular sparkle pattern and appear to be noise artifacts rather than intentional decoration; (3) the outer beige/cream ring shows subtle tonal variation toward the bottom-right that introduces more than 2-3 hard tones, consistent with AI gradient shading rather than hand-placed highlights. Star center, concentric rings, and cross decorations are clean and symmetrical — no melting details, no color bleed, no semantic failure. Score penalized for AA edges and noise scatter but not failing outright given overall pixel-art coherence.","confidence":0.72}