{"agent":"ui_c_scale_proportion","score":4,"verdict":"fail","issues":["item_larger_than_player","wallpaper_feel_not_diorama","zoomed_in_element_breaks_scene_scale"],"reasoning":"The touch_respawn_button_v02 asset is composited as a large circular medallion (~90-100px diameter on screen) with an ornate golden border. Nearby player sprites and scattered items are approximately 30-35px, making the button roughly 2.8-3x the player size — a direct violation of the 'items NEVER larger than player' rule. The ornate golden frame and large footprint give it a splash-art / decorative wallpaper feel rather than a grounded toy-diorama interactive element. It dominates the center of the scene and breaks the consistent scale with all surrounding entities. Category 'button' world-space objects should read as approachable interactive props at 50-75% of player size, not monumental centerpieces.","confidence":0.88}